verlat/__init__.py
verlat/verlat.py
verlat-0.1.0.dist-info/LICENSE
verlat-0.1.0.dist-info/WHEEL
verlat-0.1.0.dist-info/METADATA
verlat-0.1.0.dist-info/RECORD
